opal_server/__init__.py
opal_server/cli.py
opal_server/config.py
opal_server/git_fetcher.py
opal_server/loadlimiting.py
opal_server/main.py
opal_server/publisher.py
opal_server/pubsub.py
opal_server/redis_utils.py
opal_server/server.py
opal_server/statistics.py
opal_server/data/__init__.py
opal_server/data/api.py
opal_server/data/data_update_publisher.py
opal_server/policy/__init__.py
opal_server/policy/bundles/__init__.py
opal_server/policy/bundles/api.py
opal_server/policy/watcher/__init__.py
opal_server/policy/watcher/callbacks.py
opal_server/policy/watcher/factory.py
opal_server/policy/watcher/task.py
opal_server/policy/webhook/__init__.py
opal_server/policy/webhook/api.py
opal_server/policy/webhook/deps.py
opal_server/policy/webhook/listener.py
opal_server/scopes/__init__.py
opal_server/scopes/api.py
opal_server/scopes/loader.py
opal_server/scopes/scope_repository.py
opal_server/scopes/service.py
opal_server/scopes/task.py
opal_server/security/__init__.py
opal_server/security/api.py
opal_server/security/jwks.py
opal_server-0.9.0.dist-info/METADATA
opal_server-0.9.0.dist-info/WHEEL
opal_server-0.9.0.dist-info/entry_points.txt
opal_server-0.9.0.dist-info/top_level.txt
opal_server-0.9.0.dist-info/RECORD
