Metadata-Version: 2.1
Name: opal-server
Version: 0.9.0
Summary: OPAL is an administration layer for Open Policy Agent (OPA), detecting changes to both policy and data and pushing live updates to your agents. The opal-server creates a pub/sub channel clients can subscribe to (i.e: acts as coordinator). The server also tracks a git repository (via webhook) for updates to policy (or static data) and accepts continuous data update notifications via REST api, which are then pushed to clients.
Home-page: https://github.com/permitio/opal
Author: Or Weis, Asaf Cohen
Author-email: or@permit.io
License: Apache 2.0
Classifier: Operating System :: OS Independent
Classifier: License :: OSI Approved :: Apache Software License
Classifier: Programming Language :: Python
Classifier: Programming Language :: Python :: 3
Classifier: Programming Language :: Python :: 3.9
Classifier: Programming Language :: Python :: 3.10
Classifier: Programming Language :: Python :: 3.11
Classifier: Programming Language :: Python :: 3.12
Classifier: Topic :: Internet :: WWW/HTTP :: HTTP Servers
Classifier: Topic :: Internet :: WWW/HTTP :: WSGI
Requires-Python: >=3.9
Requires-Dist: click<9,>=8.1.3
Requires-Dist: permit-broadcaster[kafka,postgres,redis]==0.2.6
Requires-Dist: gitpython<4,>=3.1.32
Requires-Dist: pyjwt[crypto]<3,>=2.1.0
Requires-Dist: slowapi<1,>=0.1.5
Requires-Dist: pygit2<1.15,>=1.14.1
Requires-Dist: asgiref<4,>=3.5.2
Requires-Dist: redis<5,>=4.3.4
Requires-Dist: opal-common==0.9.0
Requires-Dist: idna<4,>=3.3
Requires-Dist: typer<1,>=0.4.1
Requires-Dist: fastapi<1,>=0.109.1
Requires-Dist: fastapi-websocket-pubsub[all]<2,>=1.0.0
Requires-Dist: fastapi-websocket-rpc<1,>=0.1.28
Requires-Dist: websockets>=10.3
Requires-Dist: gunicorn>=23.0.0
Requires-Dist: pydantic[email]<2,>=1.9.1
Requires-Dist: starlette<1,>=0.40.0
Requires-Dist: uvicorn[standard]<1,>=0.17.6
Requires-Dist: fastapi-utils<1,>=0.2.1
Requires-Dist: setuptools>=70.0.0
Requires-Dist: anyio>=4.4.0
Requires-Dist: starlette>=0.40.0
Requires-Dist: typing-extensions; python_version < "3.8"
